smoothcrawler_cluster/__init__.py
smoothcrawler_cluster/__pkg_info__.py
smoothcrawler_cluster/election.py
smoothcrawler_cluster/exceptions.py
smoothcrawler_cluster/register.py
smoothcrawler_cluster/_utils/__init__.py
smoothcrawler_cluster/_utils/converter.py
smoothcrawler_cluster/_utils/zookeeper.py
smoothcrawler_cluster/crawler/__init__.py
smoothcrawler_cluster/crawler/adapter.py
smoothcrawler_cluster/crawler/attributes.py
smoothcrawler_cluster/crawler/crawlers.py
smoothcrawler_cluster/crawler/dispatcher.py
smoothcrawler_cluster/crawler/workflow.py
smoothcrawler_cluster/model/__init__.py
smoothcrawler_cluster/model/_data.py
smoothcrawler_cluster/model/metadata.py
smoothcrawler_cluster/model/metadata_enum.py
test/_sample_components/__init__.py
test/_sample_components/_components.py
test/_sample_components/_db_mysql.py
test/_sample_components/_persistence_layer.py
test/integration_test/__init__.py
test/integration_test/register.py
test/integration_test/_test_utils/__init__.py
test/integration_test/_test_utils/_instance_value.py
test/integration_test/_test_utils/_multirunner.py
test/integration_test/_test_utils/_zk_testsuite.py
test/integration_test/_utils/__init__.py
test/integration_test/_utils/init.py
test/integration_test/_utils/zookeeper.py
test/integration_test/crawler/__init__.py
test/integration_test/crawler/_spec.py
test/integration_test/crawler/crawlers.py
test/integration_test/crawler/dispatcher.py
test/integration_test/crawler/workflow.py
test/unit_test/__init__.py
test/unit_test/election.py
test/unit_test/pkg_info.py
test/unit_test/_utils/__init__.py
test/unit_test/_utils/converter.py
test/unit_test/_utils/init.py
test/unit_test/_utils/zookeeper.py
test/unit_test/crawler/__init__.py
test/unit_test/crawler/adapter.py
test/unit_test/crawler/attributes.py
test/unit_test/crawler/crawlers.py
test/unit_test/crawler/workflow.py
test/unit_test/model/__init__.py
test/unit_test/model/_spec.py
test/unit_test/model/data.py
test/unit_test/model/init.py
SmoothCrawler_Cluster-0.2.0.dist-info/LICENSE
SmoothCrawler_Cluster-0.2.0.dist-info/METADATA
SmoothCrawler_Cluster-0.2.0.dist-info/WHEEL
SmoothCrawler_Cluster-0.2.0.dist-info/top_level.txt
SmoothCrawler_Cluster-0.2.0.dist-info/RECORD
