Metadata-Version: 2.1
Name: SmoothCrawler-Cluster
Version: 0.2.0
Summary: Develop and build web spider cluster humanly.
Home-page: https://smoothcrawler-cluster.readthedocs.io
Author: Liu, Bryant
Author-email: chi10211201@cycu.org.tw
License: Apache License 2.0
Project-URL: Documentation, https://smoothcrawler-cluster.readthedocs.io
Project-URL: Source, https://github.com/Chisanan232/SmoothCrawler-Cluster
Classifier: Development Status :: 3 - Alpha
Classifier: Intended Audience :: Developers
Classifier: Topic :: Software Development :: Libraries :: Python Modules
Classifier: License :: OSI Approved :: Apache Software License
Classifier: Operating System :: OS Independent
Classifier: Programming Language :: Python :: 3
Classifier: Programming Language :: Python :: 3.6
Classifier: Programming Language :: Python :: 3.7
Classifier: Programming Language :: Python :: 3.8
Classifier: Programming Language :: Python :: 3.9
Classifier: Programming Language :: Python :: 3.10
Classifier: Programming Language :: Python :: 3.11
Requires-Python: >=3.6
License-File: LICENSE
Requires-Dist: smoothcrawler (>=0.2.0)
Requires-Dist: kazoo (>=2.7.0)
